{"info":{"type":"runner","start":"2021-02-24T11:47:19.522Z","_duration":20655,"cid":"0-2","capabilities":{"acceptInsecureCerts":true,"browserName":"chrome","browserVersion":"88.0.4324.182","chrome":{"chromedriverVersion":"88.0.4324.96 (68dba2d8a0b149a1d3afac56fa74648032bcf46b-refs/branch-heads/4324@{#1784})","userDataDir":"C:\\Users\\LEKHAV~1\\AppData\\Local\\Temp\\scoped_dir8264_1306011840"},"goog:chromeOptions":{"debuggerAddress":"localhost:49345"},"networkConnectionEnabled":false,"pageLoadStrategy":"normal","platformName":"windows","proxy":{},"setWindowRect":true,"strictFileInteractability":false,"timeouts":{"implicit":0,"pageLoad":300000,"script":30000},"unhandledPromptBehavior":"dismiss and notify","webauthn:extension:largeBlob":true,"webauthn:virtualAuthenticators":true,"sessionId":"631c95fbb0cad10d63781ad5f30895c2"},"sanitizedCapabilities":"chrome.88_0_4324_182.windows","config":{"protocol":"http","hostname":"localhost","port":9515,"path":"/","capabilities":{"browserName":"chrome","acceptInsecureCerts":true},"logLevel":"info","connectionRetryTimeout":120000,"connectionRetryCount":3,"logLevels":{},"strictSSL":true,"requestedCapabilities":{"browserName":"chrome","acceptInsecureCerts":true},"specs":["./features/cookiepop.feature","./features/cookiesettings.feature","./features/hamburger.feature","./features/home.feature","./features/modelcolor.feature","./features/models.feature"],"exclude":[],"suites":{},"baseUrl":"http://localhost","bail":0,"waitforInterval":500,"waitforTimeout":10000,"framework":"cucumber","reporters":[[null,{"debug":true,"outputDir":"./reports/html-reports/","filename":"report.html","reportTitle":"Test Report Title","showInBrowser":true,"useOnAfterCommandForScreenshot":false}]],"services":["chromedriver"],"execArgv":[],"maxInstances":10,"maxInstancesPerCapability":100,"filesToWatch":[],"onPrepare":[null],"onWorkerStart":[],"before":[],"beforeSession":[],"beforeSuite":[],"beforeHook":[],"beforeTest":[],"beforeCommand":[],"afterCommand":[],"afterTest":[],"afterHook":[],"afterSuite":[],"afterSession":[],"after":[],"onComplete":[null],"onReload":[],"automationProtocol":"webdriver"},"specs":["C:\\Automation\\VolvoCampaign\\features\\hamburger.feature"],"sessionId":"631c95fbb0cad10d63781ad5f30895c2","isMultiremote":false,"retry":0,"failures":0,"retries":0,"end":"2021-02-24T11:47:40.177Z"},"metrics":{"passed":9,"skipped":0,"failed":0,"start":"2021-02-24T11:47:19.522Z","end":"2021-02-24T11:47:40.177Z","duration":20655},"suites":[{"type":"scenario","start":"2021-02-24T11:47:19.870Z","_duration":20235,"uid":"0","cid":"0-2","title":"Hamburger Link","fullTitle":"hamburger.feature:1:1: Hamburger Link","tags":[],"tests":[{"type":"test","start":"2021-02-24T11:47:19.875Z","_duration":17464,"uid":"11","cid":"0-2","title":"Given I open the Volvo Site","fullTitle":"0: Given I open the Volvo Site","output":[],"state":"passed","events":[],"errorIndex":0,"end":"2021-02-24T11:47:37.339Z"},{"type":"test","start":"2021-02-24T11:47:37.340Z","_duration":171,"uid":"12","cid":"0-2","title":"And I handled the cookie","fullTitle":"0: And I handled the cookie","output":[],"state":"passed","events":[],"errorIndex":0,"end":"2021-02-24T11:47:37.511Z"},{"type":"test","start":"2021-02-24T11:47:37.511Z","_duration":1555,"uid":"13","cid":"0-2","title":"Then the Campaign page should be displayed","fullTitle":"0: Then the Campaign page should be displayed","output":[],"state":"passed","events":[],"errorIndex":0,"end":"2021-02-24T11:47:39.066Z"},{"type":"test","start":"2021-02-24T11:47:39.066Z","_duration":215,"uid":"14","cid":"0-2","title":"When the user clicks on the Hamburger button","fullTitle":"0: When the user clicks on the Hamburger button","output":[],"state":"passed","events":[],"errorIndex":0,"end":"2021-02-24T11:47:39.281Z"},{"type":"test","start":"2021-02-24T11:47:39.282Z","_duration":235,"uid":"15","cid":"0-2","title":"Then option menu should be displayed","fullTitle":"0: Then option menu should be displayed","output":[],"state":"passed","events":[],"errorIndex":0,"end":"2021-02-24T11:47:39.517Z"},{"type":"test","start":"2021-02-24T11:47:39.517Z","_duration":175,"uid":"16","cid":"0-2","title":"When the user click on the first menu","fullTitle":"0: When the user click on the first menu","output":[],"state":"passed","events":[],"errorIndex":0,"end":"2021-02-24T11:47:39.692Z"},{"type":"test","start":"2021-02-24T11:47:39.692Z","_duration":143,"uid":"17","cid":"0-2","title":"Then the submenu section should be displayed","fullTitle":"0: Then the submenu section should be displayed","output":[],"state":"passed","events":[],"errorIndex":0,"end":"2021-02-24T11:47:39.835Z"},{"type":"test","start":"2021-02-24T11:47:39.835Z","_duration":223,"uid":"18","cid":"0-2","title":"When the user clicks on the close button","fullTitle":"0: When the user clicks on the close button","output":[],"state":"passed","events":[],"errorIndex":0,"end":"2021-02-24T11:47:40.058Z"},{"type":"test","start":"2021-02-24T11:47:40.058Z","_duration":46,"uid":"19","cid":"0-2","title":"And the Campaign page should be displayed","fullTitle":"0: And the Campaign page should be displayed","output":[],"state":"passed","events":[],"errorIndex":0,"end":"2021-02-24T11:47:40.104Z"}],"hooks":[{"type":"hook","start":"2021-02-24T11:47:19.870Z","_duration":5,"uid":"52","cid":"0-2","title":"","parent":"0","errors":[],"end":"2021-02-24T11:47:19.875Z"},{"type":"hook","start":"2021-02-24T11:47:40.104Z","_duration":0,"uid":"62","cid":"0-2","title":"","parent":"0","errors":[],"end":"2021-02-24T11:47:40.104Z"}],"suites":[],"hooksAndTests":[{"type":"hook","start":"2021-02-24T11:47:19.870Z","_duration":5,"uid":"52","cid":"0-2","title":"","parent":"0","errors":[],"end":"2021-02-24T11:47:19.875Z"},{"type":"test","start":"2021-02-24T11:47:19.875Z","_duration":17464,"uid":"11","cid":"0-2","title":"Given I open the Volvo Site","fullTitle":"0: Given I open the Volvo Site","output":[],"state":"passed","events":[],"errorIndex":0,"end":"2021-02-24T11:47:37.339Z"},{"type":"test","start":"2021-02-24T11:47:37.340Z","_duration":171,"uid":"12","cid":"0-2","title":"And I handled the cookie","fullTitle":"0: And I handled the cookie","output":[],"state":"passed","events":[],"errorIndex":0,"end":"2021-02-24T11:47:37.511Z"},{"type":"test","start":"2021-02-24T11:47:37.511Z","_duration":1555,"uid":"13","cid":"0-2","title":"Then the Campaign page should be displayed","fullTitle":"0: Then the Campaign page should be displayed","output":[],"state":"passed","events":[],"errorIndex":0,"end":"2021-02-24T11:47:39.066Z"},{"type":"test","start":"2021-02-24T11:47:39.066Z","_duration":215,"uid":"14","cid":"0-2","title":"When the user clicks on the Hamburger button","fullTitle":"0: When the user clicks on the Hamburger button","output":[],"state":"passed","events":[],"errorIndex":0,"end":"2021-02-24T11:47:39.281Z"},{"type":"test","start":"2021-02-24T11:47:39.282Z","_duration":235,"uid":"15","cid":"0-2","title":"Then option menu should be displayed","fullTitle":"0: Then option menu should be displayed","output":[],"state":"passed","events":[],"errorIndex":0,"end":"2021-02-24T11:47:39.517Z"},{"type":"test","start":"2021-02-24T11:47:39.517Z","_duration":175,"uid":"16","cid":"0-2","title":"When the user click on the first menu","fullTitle":"0: When the user click on the first menu","output":[],"state":"passed","events":[],"errorIndex":0,"end":"2021-02-24T11:47:39.692Z"},{"type":"test","start":"2021-02-24T11:47:39.692Z","_duration":143,"uid":"17","cid":"0-2","title":"Then the submenu section should be displayed","fullTitle":"0: Then the submenu section should be displayed","output":[],"state":"passed","events":[],"errorIndex":0,"end":"2021-02-24T11:47:39.835Z"},{"type":"test","start":"2021-02-24T11:47:39.835Z","_duration":223,"uid":"18","cid":"0-2","title":"When the user clicks on the close button","fullTitle":"0: When the user clicks on the close button","output":[],"state":"passed","events":[],"errorIndex":0,"end":"2021-02-24T11:47:40.058Z"},{"type":"test","start":"2021-02-24T11:47:40.058Z","_duration":46,"uid":"19","cid":"0-2","title":"And the Campaign page should be displayed","fullTitle":"0: And the Campaign page should be displayed","output":[],"state":"passed","events":[],"errorIndex":0,"end":"2021-02-24T11:47:40.104Z"},{"type":"hook","start":"2021-02-24T11:47:40.104Z","_duration":0,"uid":"62","cid":"0-2","title":"","parent":"0","errors":[],"end":"2021-02-24T11:47:40.104Z"}],"end":"2021-02-24T11:47:40.105Z"},{"type":"suite","start":"2021-02-24T11:47:19.870Z","_duration":0,"uid":"0","cid":"0-2","title":"Hamburger Link","fullTitle":"hamburger.feature:1:1: Hamburger Link","tags":[],"tests":[{"type":"test","start":"2021-02-24T11:47:19.875Z","_duration":17464,"uid":"11","cid":"0-2","title":"Given I open the Volvo Site","fullTitle":"0: Given I open the Volvo Site","output":[],"state":"passed","events":[],"errorIndex":0,"end":"2021-02-24T11:47:37.339Z"},{"type":"test","start":"2021-02-24T11:47:37.340Z","_duration":171,"uid":"12","cid":"0-2","title":"And I handled the cookie","fullTitle":"0: And I handled the cookie","output":[],"state":"passed","events":[],"errorIndex":0,"end":"2021-02-24T11:47:37.511Z"},{"type":"test","start":"2021-02-24T11:47:37.511Z","_duration":1555,"uid":"13","cid":"0-2","title":"Then the Campaign page should be displayed","fullTitle":"0: Then the Campaign page should be displayed","output":[],"state":"passed","events":[],"errorIndex":0,"end":"2021-02-24T11:47:39.066Z"},{"type":"test","start":"2021-02-24T11:47:39.066Z","_duration":215,"uid":"14","cid":"0-2","title":"When the user clicks on the Hamburger button","fullTitle":"0: When the user clicks on the Hamburger button","output":[],"state":"passed","events":[],"errorIndex":0,"end":"2021-02-24T11:47:39.281Z"},{"type":"test","start":"2021-02-24T11:47:39.282Z","_duration":235,"uid":"15","cid":"0-2","title":"Then option menu should be displayed","fullTitle":"0: Then option menu should be displayed","output":[],"state":"passed","events":[],"errorIndex":0,"end":"2021-02-24T11:47:39.517Z"},{"type":"test","start":"2021-02-24T11:47:39.517Z","_duration":175,"uid":"16","cid":"0-2","title":"When the user click on the first menu","fullTitle":"0: When the user click on the first menu","output":[],"state":"passed","events":[],"errorIndex":0,"end":"2021-02-24T11:47:39.692Z"},{"type":"test","start":"2021-02-24T11:47:39.692Z","_duration":143,"uid":"17","cid":"0-2","title":"Then the submenu section should be displayed","fullTitle":"0: Then the submenu section should be displayed","output":[],"state":"passed","events":[],"errorIndex":0,"end":"2021-02-24T11:47:39.835Z"},{"type":"test","start":"2021-02-24T11:47:39.835Z","_duration":223,"uid":"18","cid":"0-2","title":"When the user clicks on the close button","fullTitle":"0: When the user clicks on the close button","output":[],"state":"passed","events":[],"errorIndex":0,"end":"2021-02-24T11:47:40.058Z"},{"type":"test","start":"2021-02-24T11:47:40.058Z","_duration":46,"uid":"19","cid":"0-2","title":"And the Campaign page should be displayed","fullTitle":"0: And the Campaign page should be displayed","output":[],"state":"passed","events":[],"errorIndex":0,"end":"2021-02-24T11:47:40.104Z"}],"hooks":[{"type":"hook","start":"2021-02-24T11:47:19.870Z","_duration":5,"uid":"52","cid":"0-2","title":"","parent":"0","errors":[],"end":"2021-02-24T11:47:19.875Z"},{"type":"hook","start":"2021-02-24T11:47:40.104Z","_duration":0,"uid":"62","cid":"0-2","title":"","parent":"0","errors":[],"end":"2021-02-24T11:47:40.104Z"}],"suites":[],"hooksAndTests":[{"type":"hook","start":"2021-02-24T11:47:19.870Z","_duration":5,"uid":"52","cid":"0-2","title":"","parent":"0","errors":[],"end":"2021-02-24T11:47:19.875Z"},{"type":"test","start":"2021-02-24T11:47:19.875Z","_duration":17464,"uid":"11","cid":"0-2","title":"Given I open the Volvo Site","fullTitle":"0: Given I open the Volvo Site","output":[],"state":"passed","events":[],"errorIndex":0,"end":"2021-02-24T11:47:37.339Z"},{"type":"test","start":"2021-02-24T11:47:37.340Z","_duration":171,"uid":"12","cid":"0-2","title":"And I handled the cookie","fullTitle":"0: And I handled the cookie","output":[],"state":"passed","events":[],"errorIndex":0,"end":"2021-02-24T11:47:37.511Z"},{"type":"test","start":"2021-02-24T11:47:37.511Z","_duration":1555,"uid":"13","cid":"0-2","title":"Then the Campaign page should be displayed","fullTitle":"0: Then the Campaign page should be displayed","output":[],"state":"passed","events":[],"errorIndex":0,"end":"2021-02-24T11:47:39.066Z"},{"type":"test","start":"2021-02-24T11:47:39.066Z","_duration":215,"uid":"14","cid":"0-2","title":"When the user clicks on the Hamburger button","fullTitle":"0: When the user clicks on the Hamburger button","output":[],"state":"passed","events":[],"errorIndex":0,"end":"2021-02-24T11:47:39.281Z"},{"type":"test","start":"2021-02-24T11:47:39.282Z","_duration":235,"uid":"15","cid":"0-2","title":"Then option menu should be displayed","fullTitle":"0: Then option menu should be displayed","output":[],"state":"passed","events":[],"errorIndex":0,"end":"2021-02-24T11:47:39.517Z"},{"type":"test","start":"2021-02-24T11:47:39.517Z","_duration":175,"uid":"16","cid":"0-2","title":"When the user click on the first menu","fullTitle":"0: When the user click on the first menu","output":[],"state":"passed","events":[],"errorIndex":0,"end":"2021-02-24T11:47:39.692Z"},{"type":"test","start":"2021-02-24T11:47:39.692Z","_duration":143,"uid":"17","cid":"0-2","title":"Then the submenu section should be displayed","fullTitle":"0: Then the submenu section should be displayed","output":[],"state":"passed","events":[],"errorIndex":0,"end":"2021-02-24T11:47:39.835Z"},{"type":"test","start":"2021-02-24T11:47:39.835Z","_duration":223,"uid":"18","cid":"0-2","title":"When the user clicks on the close button","fullTitle":"0: When the user clicks on the close button","output":[],"state":"passed","events":[],"errorIndex":0,"end":"2021-02-24T11:47:40.058Z"},{"type":"test","start":"2021-02-24T11:47:40.058Z","_duration":46,"uid":"19","cid":"0-2","title":"And the Campaign page should be displayed","fullTitle":"0: And the Campaign page should be displayed","output":[],"state":"passed","events":[],"errorIndex":0,"end":"2021-02-24T11:47:40.104Z"},{"type":"hook","start":"2021-02-24T11:47:40.104Z","_duration":0,"uid":"62","cid":"0-2","title":"","parent":"0","errors":[],"end":"2021-02-24T11:47:40.104Z"}]}],"title":"Test Report Title"}